srne/__init__.py
srne/constants.py
srne/controller.py
srne/modbus.py
srne/tools.py
srne/register/__init__.py
srne/register/data.py
srne/register/decoder.py
srne/register/encoder.py
srne/register/factory.py
srne/register/sequencer.py
srne-0.8.4.dist-info/LICENSE
srne-0.8.4.dist-info/METADATA
srne-0.8.4.dist-info/WHEEL
srne-0.8.4.dist-info/top_level.txt
srne-0.8.4.dist-info/RECORD
