Metadata-Version: 2.1
Name: srne
Version: 0.8.4
Summary: A library for SRNE compatible devices.
Author-email: adorjanw <adorjanw@outlook.com>
Project-URL: Homepage, https://github.com/adorjanw/srne-python
Classifier: Programming Language :: Python :: 3
Classifier: License :: OSI Approved :: MIT License
Classifier: Operating System :: OS Independent
Classifier: Topic :: Software Development :: Libraries
Requires-Python: >=3.7.3
License-File: LICENSE
Requires-Dist: pyserial ==3.5
